CHANGES.rst
LICENSE
MANIFEST.in
README.rst
VERSION
requirements.txt
setup.py
cms/__init__.py
cms/__init__.pyc
cms/events.py
cms/events.pyc
cms/tasks.py
cms/tasks.pyc
cms/utils.py
cms/utils.pyc
cms/static/pyramid-16x16.png
cms/static/pyramid.png
cms/static/theme.css
cms/static/theme.min.css
cms/static/css/style.css
cms/static/img/facebook.png
cms/static/img/favicon.ico
cms/static/img/icon-diarrhoea.jpg
cms/static/img/icon-facebook.png
cms/static/img/icon-hygiene.jpg
cms/static/img/icon-twitter.png
cms/static/img/kids.jpg
cms/static/img/logo-unaids.png
cms/static/img/logo-undp.png
cms/static/img/logo-unesco.png
cms/static/img/logo-unfpa.png
cms/static/img/logo-unicef.png
cms/static/img/logo-wfp.png
cms/static/img/logo-who.png
cms/static/img/logo-world-bank.png
cms/static/img/logo.png
cms/static/img/twitter.png
cms/static/js/jquery.rest.min.js
cms/templates/404.jinja2
cms/templates/404.pt
cms/templates/atoms.html
cms/templates/auth.pt
cms/templates/base.jinja2
cms/templates/base.pt
cms/templates/categories.pt
cms/templates/category.jinja2
cms/templates/category.pt
cms/templates/content.jinja2
cms/templates/content.pt
cms/templates/flatpage.jinja2
cms/templates/flatpage.pt
cms/templates/form_utils.jinja2
cms/templates/home.jinja2
cms/templates/home.pt
cms/templates/locale_change.jinja2
cms/templates/locale_change.pt
cms/templates/logo.pt
cms/templates/molecules.html
cms/templates/organisms.html
cms/templates/paginator.pt
cms/templates/paginator_category.pt
cms/templates/search_box.pt
cms/templates/search_results.jinja2
cms/templates/search_results.pt
cms/templates/admin/configure.pt
cms/templates/admin/home.pt
cms/templates/comments/comment.jinja2
cms/templates/comments/comment_flagged.jinja2
cms/templates/comments/comment_form.jinja2
cms/templates/comments/comment_list.jinja2
cms/templates/comments/comment_page.jinja2
cms/tests/__init__.py
cms/tests/__init__.pyc
cms/tests/base.py
cms/tests/base.pyc
cms/tests/test_auth.py
cms/tests/test_comments.py
unicore_cms.egg-info/PKG-INFO
unicore_cms.egg-info/SOURCES.txt
unicore_cms.egg-info/dependency_links.txt
unicore_cms.egg-info/entry_points.txt
unicore_cms.egg-info/not-zip-safe
unicore_cms.egg-info/requires.txt
unicore_cms.egg-info/top_level.txt