Metadata-Version: 1.1
Name: unicore-cms
Version: 1.9.8
Summary: JSON based CMS for Universal Core
Home-page: http://github.com/universalcore/unicore-cms
Author: Praekelt Foundation
Author-email: dev@praekelt.com
License: BSD
Keywords: web pyramid pylons
Platform: UNKNOWN
Classifier: Programming Language :: Python
Classifier: Framework :: Pyramid
Classifier: Topic :: Internet :: WWW/HTTP
Classifier: Topic :: Internet :: WWW/HTTP :: WSGI :: Application
